survinsights/__init__.py
survinsights/explainer.py
survinsights/performance.py
survinsights/prediction.py
survinsights/utils.py
survinsights/global_explaination/__init__.py
survinsights/global_explaination/_ale.py
survinsights/global_explaination/_fi.py
survinsights/global_explaination/_pdp.py
survinsights/global_explaination/_pfi.py
survinsights/local_explaination/__init__.py
survinsights/local_explaination/_ice.py
survinsights/local_explaination/_survlime.py
survinsights/local_explaination/_survshap.py
survinsights-0.0.3.dist-info/METADATA
survinsights-0.0.3.dist-info/WHEEL
survinsights-0.0.3.dist-info/licenses/LICENSE
survinsights-0.0.3.dist-info/RECORD
